harmon_ai/__init__.py
harmon_ai/cli.py
harmon_ai/harmon_ai.py
harmon_ai/utils.py
harmon_ai/templates/__init__.py
harmon_ai/templates/badges_template.md
harmon_ai/templates/config.example.yml
harmon_ai/templates/important_template.md
harmon_ai/templates/publish-to-pypi.yml
harmon_ai/templates/readme_template.md
harmon_ai/templates/sections_template.md
harmon_ai/templates/sns_template.md
harmon_ai-1.5.1.dist-info/LICENSE
harmon_ai-1.5.1.dist-info/METADATA
harmon_ai-1.5.1.dist-info/WHEEL
harmon_ai-1.5.1.dist-info/entry_points.txt
harmon_ai-1.5.1.dist-info/top_level.txt
harmon_ai-1.5.1.dist-info/RECORD
